striker/__init__.py
striker/_cli.py
striker/_engine.py
striker/_parameter.py
striker/core/__init__.py
striker/core/_base/__init__.py
striker/core/_base/_base.py
striker/core/_base/_manager.py
striker/core/_base/_parent.py
striker/core/_protocol.py
striker/core/_weakref.py
striker/core/hook/__init__.py
striker/core/hook/_factory.py
striker/core/hook/_hook.py
striker/core/hook/_manager.py
striker/core/hook/_parent.py
striker/core/mixin/__init__.py
striker/core/mixin/_data.py
striker/core/mixin/_engine.py
striker/core/mixin/_loop.py
striker/core/mixin/_mixin.py
striker/core/plugin/__init__.py
striker/core/plugin/_plugin.py
striker/mixins/__init__.py
striker/mixins/data_property.py
striker/mixins/engine_test.py
striker/mixins/engine_train.py
striker/mixins/engine_trainvalidation.py
striker/mixins/loop_batchtrain.py
striker/mixins/loop_minibatchtrain.py
striker/mixins/loop_test.py
striker/plugins/__init__.py
striker/plugins/backup.py
striker/plugins/device.py
striker/plugins/log.py
striker/plugins/progress.py
striker/plugins/quit.py
striker-0.3.0.dist-info/LICENSE
striker-0.3.0.dist-info/WHEEL
striker-0.3.0.dist-info/METADATA
striker-0.3.0.dist-info/RECORD
